{
  "apiType": "stageMode",
  "buildOption": {
    "arkOptions": {
      "runtimeOnly": {
        "packages": [
          'tobid_kuaishou_adapter',
          'tobid_huawei_adapter',
          'tobid_csj_adapter',
          'tobid_gromore_adapter'
        ]
      }
    }
  },
  "buildOptionSet": [
    {
      "name": "release",
      "arkOptions": {
        "obfuscation": {
          "ruleOptions": {
            "enable": false,
            "files": [
              "./obfuscation-rules.txt"
            ]
          }
        }
      }
    },
  ],
  "targets": [
    {
      "name": "default"
    },
    {
      "name": "ohosTest",
    }
  ]
}